bigTpuProfile/__init__.py
bigTpuProfile/_version.py
bigTpuProfile/bmprofile_perfAI_2260.py
bigTpuProfile/main.py
bigTpuProfile/setup.py
bigTpuProfile/debugger/__init__.py
bigTpuProfile/debugger/target_1690/__init__.py
bigTpuProfile/debugger/target_1690/context.py
bigTpuProfile/debugger/target_1690/decoder.py
bigTpuProfile/debugger/target_1690/memmap.py
bigTpuProfile/debugger/target_1690/multi_core.py
bigTpuProfile/debugger/target_1690/opdef.py
bigTpuProfile/debugger/target_1690/opparam.py
bigTpuProfile/debugger/target_1690/regdef.py
bigTpuProfile/debugger/target_1690/xlsx_to_py.py
bigTpuProfile/debugger/target_common/__init__.py
bigTpuProfile/debugger/target_common/context.py
bigTpuProfile/debugger/target_common/decoder.py
bigTpuProfile/debugger/target_common/op_support.py
bigTpuProfile/debugger/target_common/runner.py
bigTpuProfile/perfAI/__init__.py
bigTpuProfile/perfAI/perfAIDoc/__init__.py
bigTpuProfile/perfAI/perfAIDoc/run_doc.py
bigTpuProfile/perfAI/perfAIDoc/run_summary.py
bigTpuProfile/perfAI/perfAIDoc/definition/__init__.py
bigTpuProfile/perfAI/perfAIDoc/definition/bm1684x_defs.py
bigTpuProfile/perfAI/perfAIDoc/definition/style.py
bigTpuProfile/perfAI/perfAIDoc/include/ABCSet_summary.py
bigTpuProfile/perfAI/perfAIDoc/include/__init__.py
bigTpuProfile/perfAI/perfAIDoc/include/asic_summary.py
bigTpuProfile/perfAI/perfAIDoc/include/dma.py
bigTpuProfile/perfAI/perfAIDoc/include/instr_world.py
bigTpuProfile/perfAI/perfAIDoc/include/layer.py
bigTpuProfile/perfAI/perfAIDoc/include/summary.py
bigTpuProfile/perfAI/perfAIDoc/include/tiu.py
bigTpuProfile/perfAI/perfAIDoc/src/__init__.py
bigTpuProfile/perfAI/perfAIDoc/src/common/__init__.py
bigTpuProfile/perfAI/perfAIDoc/src/common/common.py
bigTpuProfile/perfAI/perfAIDoc/src/generator/__init__.py
bigTpuProfile/perfAI/perfAIDoc/src/generator/details.py
bigTpuProfile/perfAI/perfAIDoc/src/generator/layer.py
bigTpuProfile/perfAI/perfAIDoc/src/generator/style.py
bigTpuProfile/perfAI/perfAIDoc/src/generator/summary.py
bigtpuprofile-0.2.1.dist-info/METADATA
bigtpuprofile-0.2.1.dist-info/WHEEL
bigtpuprofile-0.2.1.dist-info/entry_points.txt
bigtpuprofile-0.2.1.dist-info/top_level.txt
bigtpuprofile-0.2.1.dist-info/RECORD
