Metadata-Version: 2.4
Name: bigTpuProfile
Version: 0.2.1
Summary: A profile visualization tool for bm1690
Home-page: 
Author: shaoxiong.xiang
Author-email: shaoxiong.xiang@icloud.com
Classifier: Programming Language :: Python :: 3
Classifier: License :: OSI Approved :: MIT License
Classifier: Operating System :: OS Independent
Requires-Python: >=3.7
Requires-Dist: pandas
Requires-Dist: bs4
Requires-Dist: openpyxl
Requires-Dist: numpy
Dynamic: author
Dynamic: author-email
Dynamic: classifier
Dynamic: description
Dynamic: description-content-type
Dynamic: requires-dist
Dynamic: requires-python
Dynamic: summary
